marshmallow_select/__init__.py
marshmallow_select/schema_filter.py
marshmallow_select/xxx.py
marshmallow_select-1.0.5.dist-info/DESCRIPTION.rst
marshmallow_select-1.0.5.dist-info/METADATA
marshmallow_select-1.0.5.dist-info/RECORD
marshmallow_select-1.0.5.dist-info/WHEEL
marshmallow_select-1.0.5.dist-info/metadata.json
marshmallow_select-1.0.5.dist-info/top_level.txt
tests/__init__.py
tests/test_marshmallow_select.py
tests/yyy.py
