Metadata-Version: 2.0
Name: marshmallow-select
Version: 1.0.5
Summary: make sqlalchemy select fields with marshmallow schemas
Home-page: https://github.com/marshmallow-code/marshmallow-select
Author: dmr
Author-email: dradetsky@gmail.com
License: WTFPL
Keywords: marshmallow,sqlalchemy
Platform: UNKNOWN
Classifier: Development Status :: 3 - Alpha
Classifier: Intended Audience :: Developers
Classifier: License :: DFSG approved
Classifier: License :: Freely Distributable
Classifier: License :: Public Domain
Classifier: Natural Language :: English
Classifier: Programming Language :: Python :: 3
Classifier: Programming Language :: Python :: 3.4
Classifier: Programming Language :: Python :: 3.5
Classifier: Programming Language :: Python :: 3.6
Classifier: Topic :: Database
Requires-Dist: SQLAlchemy (>=1.1.6)
Requires-Dist: marshmallow (>=2.10.3)
